ImageEncDec/__init__.py
ImageEncDec/enc_dec.py
image_enc_dec-0.0.1.dist-info/LICENSE
image_enc_dec-0.0.1.dist-info/METADATA
image_enc_dec-0.0.1.dist-info/WHEEL
image_enc_dec-0.0.1.dist-info/top_level.txt
image_enc_dec-0.0.1.dist-info/RECORD
