Metadata-Version: 2.1
Name: image-enc-dec
Version: 0.0.1
Summary: A python application for image encryption decryption
Home-page: https://github.com/CodderscluB/Image_Encryption_Decryption/
Author: Tejas Dixit(PANDATD)
Author-email: <coddersclub@gmail.com>
License: UNKNOWN
Project-URL: Bug Tracker, https://github.com/CodderscluB/Image_Encryption_Decryption/issues
Project-URL: Maintainer, https://github.com/pandatd/
Project-URL: Blog, https://medium.com/coddersclub
Keywords: python,encryption,decryption,encryptiondecryption
Platform: UNKNOWN
Classifier: Development Status :: 1 - Planning
Classifier: Intended Audience :: Developers
Classifier: Programming Language :: Python :: 3
Classifier: Operating System :: Unix
Classifier: Operating System :: MacOS :: MacOS X
Classifier: Operating System :: Microsoft :: Windows
Requires-Dist: tk
